LittleAspNetCoreBook/README.md
LittleAspNetCoreBook/__init__.py
LittleAspNetCoreBook/__main__.py
LittleAspNetCoreBook/file.epub
LittleAspNetCoreBook/index.html
LittleAspNetCoreBook/css/__init__.py
LittleAspNetCoreBook/css/annotations.css
LittleAspNetCoreBook/css/main.css
LittleAspNetCoreBook/css/normalize.css
LittleAspNetCoreBook/css/popup.css
LittleAspNetCoreBook/font/__init__.py
LittleAspNetCoreBook/font/fontello.eot
LittleAspNetCoreBook/font/fontello.svg
LittleAspNetCoreBook/font/fontello.ttf
LittleAspNetCoreBook/font/fontello.woff
LittleAspNetCoreBook/img/__init__.py
LittleAspNetCoreBook/img/annotator-glyph-sprite.png
LittleAspNetCoreBook/img/annotator-icon-sprite.png
LittleAspNetCoreBook/img/apple-touch-icon.png
LittleAspNetCoreBook/img/cancelfullscreen.png
LittleAspNetCoreBook/img/close.png
LittleAspNetCoreBook/img/fullscreen.png
LittleAspNetCoreBook/img/loader.gif
LittleAspNetCoreBook/img/menu-icon.png
LittleAspNetCoreBook/img/save.png
LittleAspNetCoreBook/img/saved.png
LittleAspNetCoreBook/img/settings-s.png
LittleAspNetCoreBook/img/settings.png
LittleAspNetCoreBook/img/star.png
LittleAspNetCoreBook/js/__init__.py
LittleAspNetCoreBook/js/epub.js
LittleAspNetCoreBook/js/epub.min.js
LittleAspNetCoreBook/js/epub.min.map
LittleAspNetCoreBook/js/hooks.min.js
LittleAspNetCoreBook/js/hooks.min.map
LittleAspNetCoreBook/js/reader.js
LittleAspNetCoreBook/js/reader.js.map
LittleAspNetCoreBook/js/reader.min.js
LittleAspNetCoreBook/js/reader.min.map
LittleAspNetCoreBook/js/hooks/__init__.py
LittleAspNetCoreBook/js/hooks/extensions/__init__.py
LittleAspNetCoreBook/js/hooks/extensions/highlight.js
LittleAspNetCoreBook/js/libs/__init__.py
LittleAspNetCoreBook/js/libs/jquery.min.js
LittleAspNetCoreBook/js/libs/localforage.min.js
LittleAspNetCoreBook/js/libs/screenfull.js
LittleAspNetCoreBook/js/libs/screenfull.min.js
LittleAspNetCoreBook/js/libs/zip.min.js
LittleAspNetCoreBook/js/plugins/__init__.py
LittleAspNetCoreBook/js/plugins/hypothesis.js
little_asp_net_core_book-2024.3.3.0.dist-info/METADATA
little_asp_net_core_book-2024.3.3.0.dist-info/WHEEL
little_asp_net_core_book-2024.3.3.0.dist-info/entry_points.txt
little_asp_net_core_book-2024.3.3.0.dist-info/top_level.txt
little_asp_net_core_book-2024.3.3.0.dist-info/RECORD
